odoo/addons/fieldservice_skill/README.rst
odoo/addons/fieldservice_skill/__init__.py
odoo/addons/fieldservice_skill/__manifest__.py
odoo/addons/fieldservice_skill/models/__init__.py
odoo/addons/fieldservice_skill/models/fsm_category.py
odoo/addons/fieldservice_skill/models/fsm_order.py
odoo/addons/fieldservice_skill/models/fsm_person.py
odoo/addons/fieldservice_skill/models/fsm_person_skill.py
odoo/addons/fieldservice_skill/readme/CONFIGURE.rst
odoo/addons/fieldservice_skill/readme/CONTRIBUTORS.rst
odoo/addons/fieldservice_skill/readme/CREDITS.rst
odoo/addons/fieldservice_skill/readme/DESCRIPTION.rst
odoo/addons/fieldservice_skill/readme/INSTALL.rst
odoo/addons/fieldservice_skill/readme/ROADMAP.rst
odoo/addons/fieldservice_skill/readme/USAGE.rst
odoo/addons/fieldservice_skill/security/ir.model.access.csv
odoo/addons/fieldservice_skill/static/description/icon.png
odoo/addons/fieldservice_skill/static/description/index.html
odoo/addons/fieldservice_skill/views/fsm_category.xml
odoo/addons/fieldservice_skill/views/fsm_order.xml
odoo/addons/fieldservice_skill/views/fsm_person.xml
odoo/addons/fieldservice_skill/views/fsm_person_skill.xml
odoo/addons/fieldservice_skill/views/hr_skill.xml
odoo11_addon_fieldservice_skill-11.0.0.1.0.dist-info/METADATA
odoo11_addon_fieldservice_skill-11.0.0.1.0.dist-info/RECORD
odoo11_addon_fieldservice_skill-11.0.0.1.0.dist-info/WHEEL
odoo11_addon_fieldservice_skill-11.0.0.1.0.dist-info/top_level.txt
